TracDashesSyntaxPlugin-1.1.dist-info/METADATA
TracDashesSyntaxPlugin-1.1.dist-info/RECORD
TracDashesSyntaxPlugin-1.1.dist-info/WHEEL
TracDashesSyntaxPlugin-1.1.dist-info/entry_points.txt
TracDashesSyntaxPlugin-1.1.dist-info/top_level.txt
tracdashessyntax/__init__.py
tracdashessyntax/plugin.py
